percolate/__init__.py
percolate/hpc.py
percolate/percolate.py
percolate/share/jugfile.py
percolate/test/__init__.py
percolate/test/test_hpc.py
percolate/test/test_percolate.py
percolate-0.4.6.dist-info/DESCRIPTION.rst
percolate-0.4.6.dist-info/METADATA
percolate-0.4.6.dist-info/RECORD
percolate-0.4.6.dist-info/WHEEL
percolate-0.4.6.dist-info/entry_points.txt
percolate-0.4.6.dist-info/metadata.json
percolate-0.4.6.dist-info/namespace_packages.txt
percolate-0.4.6.dist-info/top_level.txt
