Metadata-Version: 2.0
Name: percolate
Version: 0.4.6
Summary: A scientific Python package for Monte Carlo simulation of percolation on graphs
Home-page: http://pypercolate.readthedocs.org
Author: Andreas Sorge
Author-email: pypercolate@asorge.de
License: isc
Platform: UNKNOWN
Classifier: Development Status :: 3 - Alpha
Classifier: Intended Audience :: Science/Research
Classifier: License :: OSI Approved :: ISC License (ISCL)
Classifier: Programming Language :: Python
Classifier: Programming Language :: Python :: 2.7
Classifier: Programming Language :: Python :: 3.4
Classifier: Programming Language :: Python :: 3.5
Classifier: Topic :: Scientific/Engineering :: Mathematics
Classifier: Topic :: Scientific/Engineering :: Physics
Requires-Dist: future
Requires-Dist: networkx
Requires-Dist: numpy
Requires-Dist: scipy
Requires-Dist: simoa
